effluent/__init__.py
effluent/__main__.py
effluent/eos.py
effluent/io.py
effluent/model.py
effluent/numerics.py
effluent/roms.py
effluent/script.py
effluent/solver.py
effluent-1.5.0.dist-info/LICENSE
effluent-1.5.0.dist-info/METADATA
effluent-1.5.0.dist-info/WHEEL
effluent-1.5.0.dist-info/entry_points.txt
effluent-1.5.0.dist-info/top_level.txt
effluent-1.5.0.dist-info/RECORD
