Metadata-Version: 2.1
Name: effluent
Version: 1.5.0
Summary: Simulate effluent discharges from wastewater pipes
Home-page: https://github.com/pnsaevik/effluent
Author: Pål Næverlid Sævik
Author-email: paal.naeverlid.saevik@hi.no
Project-URL: Documentation, https://effluent.readthedocs.io/en/latest/
Project-URL: Changelog, https://github.com/pnsaevik/effluent/blob/main/CHANGELOG.md
Keywords: pipes turbulent jets plumes ocean
Classifier: Development Status :: 1 - Planning
Classifier: License :: OSI Approved :: MIT License
Classifier: Natural Language :: English
Classifier: Operating System :: OS Independent
Classifier: Programming Language :: Python
Classifier: Intended Audience :: Science/Research
Classifier: Topic :: Scientific/Engineering
Requires-Python: >=3.6
License-File: LICENSE
Requires-Dist: numpy
Requires-Dist: xarray
Requires-Dist: pandas
Requires-Dist: netcdf4
Requires-Dist: scipy
Requires-Dist: tomli
Provides-Extra: dev
Requires-Dist: pytest ; extra == 'dev'
Requires-Dist: matplotlib ; extra == 'dev'
Requires-Dist: sphinx ; extra == 'dev'
Requires-Dist: sphinx-autoapi ; extra == 'dev'
